CHANGELOG.txt
LICENSE.txt
MANIFEST.in
README.txt
__init__.py
calculatorpackage.py
setup.py
Pallavi_Calculator.egg-info/PKG-INFO
Pallavi_Calculator.egg-info/SOURCES.txt
Pallavi_Calculator.egg-info/dependency_links.txt
Pallavi_Calculator.egg-info/top_level.txt